gwlib/__init__.py
gwlib/base/__init__.py
gwlib/base/base_controller.py
gwlib/base/base_dao.py
gwlib/base/base_service.py
gwlib/base/errors.py
gwlib/config/__init__.py
gwlib/config/default.py
gwlib/config/development.py
gwlib/config/production.py
gwlib/dao/__init__.py
gwlib/dao/alert_dao.py
gwlib/dao/golf_course_dao.py
gwlib/dao/holes_dao.py
gwlib/dao/menu_dao.py
gwlib/dao/report_dao.py
gwlib/dao/resource_dao.py
gwlib/dao/sensor_dao.py
gwlib/dao/user_dao.py
gwlib/dao/user_policy_dao.py
gwlib/dao/user_token_dao.py
gwlib/http/__init__.py
gwlib/http/responses.py
gwlib/http/types.py
gwlib/models/Alert.py
gwlib/models/GolfCourse.py
gwlib/models/Hole.py
gwlib/models/Report.py
gwlib/models/Resource.py
gwlib/models/Sensor.py
gwlib/models/User.py
gwlib/models/UserToken.py
gwlib/models/UserType.py
gwlib/models/UserTypePolicy.py
gwlib/models/Zone.py
gwlib/models/ZoneLocation.py
gwlib/models/ZoneQuadrant.py
gwlib/models/__init__.py
gwlib/models/menu.py
gwlib/models/model_json.py
gwlib/models/user_golf_course.py
gwlib/models/user_type_menu.py
gwlib/security/__init__.py
gwlib/security/decorators.py
gwlib/services/__init__.py
gwlib/services/base_alert_service.py
gwlib/services/base_course_service.py
gwlib/services/base_holes_service.py
gwlib/services/base_menu_service.py
gwlib/services/base_policy_service.py
gwlib/services/base_report_service.py
gwlib/services/base_resource.py
gwlib/services/base_sensor_service.py
gwlib/services/base_upload_service.py
gwlib/services/base_user_service.py
gwlib/utils/__init__.py
gwlib/utils/consts.py
gwlib/utils/helper.py
gw_md_lib-0.10.57.dist-info/LICENSE
gw_md_lib-0.10.57.dist-info/METADATA
gw_md_lib-0.10.57.dist-info/WHEEL
gw_md_lib-0.10.57.dist-info/top_level.txt
gw_md_lib-0.10.57.dist-info/RECORD
