Metadata-Version: 2.1
Name: gw-md-lib
Version: 0.10.57
Summary: Common lib to GW project
Home-page: UNKNOWN
Author: Auriz
Author-email: edominguez@auriz.biz
License: UNKNOWN
Platform: UNKNOWN
Classifier: Programming Language :: Python :: 3
Classifier: License :: OSI Approved :: MIT License
Classifier: Operating System :: OS Independent
Requires-Python: >=3.6
Requires-Dist: Flask
Requires-Dist: boto3 (==1.12.41)
Requires-Dist: Flask-SQLAlchemy (==2.4.0)
Requires-Dist: Flask-JWT-Extended (==3.21.0)
Requires-Dist: sendgrid
